CssQuanweiZhinanZhongwenDisiban/README.md
CssQuanweiZhinanZhongwenDisiban/__init__.py
CssQuanweiZhinanZhongwenDisiban/__main__.py
CssQuanweiZhinanZhongwenDisiban/file.epub
CssQuanweiZhinanZhongwenDisiban/index.html
CssQuanweiZhinanZhongwenDisiban/css/__init__.py
CssQuanweiZhinanZhongwenDisiban/css/annotations.css
CssQuanweiZhinanZhongwenDisiban/css/main.css
CssQuanweiZhinanZhongwenDisiban/css/normalize.css
CssQuanweiZhinanZhongwenDisiban/css/popup.css
CssQuanweiZhinanZhongwenDisiban/font/__init__.py
CssQuanweiZhinanZhongwenDisiban/font/fontello.eot
CssQuanweiZhinanZhongwenDisiban/font/fontello.svg
CssQuanweiZhinanZhongwenDisiban/font/fontello.ttf
CssQuanweiZhinanZhongwenDisiban/font/fontello.woff
CssQuanweiZhinanZhongwenDisiban/img/__init__.py
CssQuanweiZhinanZhongwenDisiban/img/annotator-glyph-sprite.png
CssQuanweiZhinanZhongwenDisiban/img/annotator-icon-sprite.png
CssQuanweiZhinanZhongwenDisiban/img/apple-touch-icon.png
CssQuanweiZhinanZhongwenDisiban/img/cancelfullscreen.png
CssQuanweiZhinanZhongwenDisiban/img/close.png
CssQuanweiZhinanZhongwenDisiban/img/fullscreen.png
CssQuanweiZhinanZhongwenDisiban/img/loader.gif
CssQuanweiZhinanZhongwenDisiban/img/menu-icon.png
CssQuanweiZhinanZhongwenDisiban/img/save.png
CssQuanweiZhinanZhongwenDisiban/img/saved.png
CssQuanweiZhinanZhongwenDisiban/img/settings-s.png
CssQuanweiZhinanZhongwenDisiban/img/settings.png
CssQuanweiZhinanZhongwenDisiban/img/star.png
CssQuanweiZhinanZhongwenDisiban/js/__init__.py
CssQuanweiZhinanZhongwenDisiban/js/epub.js
CssQuanweiZhinanZhongwenDisiban/js/epub.min.js
CssQuanweiZhinanZhongwenDisiban/js/epub.min.map
CssQuanweiZhinanZhongwenDisiban/js/hooks.min.js
CssQuanweiZhinanZhongwenDisiban/js/hooks.min.map
CssQuanweiZhinanZhongwenDisiban/js/reader.js
CssQuanweiZhinanZhongwenDisiban/js/reader.js.map
CssQuanweiZhinanZhongwenDisiban/js/reader.min.js
CssQuanweiZhinanZhongwenDisiban/js/reader.min.map
CssQuanweiZhinanZhongwenDisiban/js/hooks/__init__.py
css_quanwei_zhinan_zhongwen_disiban-2024.3.5.0.dist-info/METADATA
css_quanwei_zhinan_zhongwen_disiban-2024.3.5.0.dist-info/WHEEL
css_quanwei_zhinan_zhongwen_disiban-2024.3.5.0.dist-info/entry_points.txt
css_quanwei_zhinan_zhongwen_disiban-2024.3.5.0.dist-info/top_level.txt
css_quanwei_zhinan_zhongwen_disiban-2024.3.5.0.dist-info/RECORD
